Workbook

Sheet data_clean
A1: date | B1: xr | C1: infl_diff | D1: tot | E1: nfa | F1: ir_diff | G1: cds
A2: 40179 | B2: =LN(Sheet2!B3) -> 9.1447346 | C2: =Sheet2!E3 -> 2.9165015 | D2: =Sheet2!H3 -> 0.30526427 | E2: =Sheet2!I3 -> 13.479959 | F2: =Sheet2!L3 -> 6.39 | G2: =LN(Sheet2!M3) -> 5.2540649
A3: 40210 | B3: =LN(Sheet2!B4) -> 9.1415261 | C3: =Sheet2!E4 -> 2.5310936 | D3: =Sheet2!H4 -> 0.38158876 | E3: =Sheet2!I4 -> 13.481849 | F3: =Sheet2!L4 -> 6.37 | G3: =LN(Sheet2!M4) -> 5.3123724
A4: 40238 | B4: =LN(Sheet2!B5) -> 9.1176767 | C4: =Sheet2!E5 -> 2.4007758 | D4: =Sheet2!H5 -> 0.36406973 | E4: =Sheet2!I5 -> 13.49557 | F4: =Sheet2!L5 -> 6.34 | G4: =LN(Sheet2!M5) -> 5.0942627
A5: 40269 | B5: =LN(Sheet2!B6) -> 9.1063123 | C5: =Sheet2!E6 -> 2.7276196 | D5: =Sheet2!H6 -> 0.38944441 | E5: =Sheet2!I6 -> 13.559525 | F5: =Sheet2!L6 -> 6.3 | G5: =LN(Sheet2!M6) -> 5.074183
A6: 40299 | B6: =LN(Sheet2!B7) -> 9.1247825 | C6: =Sheet2!E7 -> 2.8745497 | D6: =Sheet2!H7 -> 0.37333009 | E6: =Sheet2!I7 -> 13.506323 | F6: =Sheet2!L7 -> 6.3 | G6: =LN(Sheet2!M7) -> 5.228219
A7: 40330 | B7: =LN(Sheet2!B8) -> 9.1141598 | C7: =Sheet2!E8 -> 3.0167862 | D7: =Sheet2!H8 -> 0.36313937 | E7: =Sheet2!I8 -> 13.536574 | F7: =Sheet2!L8 -> 6.32 | G7: =LN(Sheet2!M8) -> 5.2059035
A8: 40360 | B8: =LN(Sheet2!B9) -> 9.0996322 | C8: =Sheet2!E9 -> 3.1915909 | D8: =Sheet2!H9 -> 0.44123301 | E8: =Sheet2!I9 -> 13.543568 | F8: =Sheet2!L9 -> 6.32 | G8: =LN(Sheet2!M9) -> 5.1161175
A9: 40391 | B9: =LN(Sheet2!B10) -> 9.1095251 | C9: =Sheet2!E10 -> 3.3200388 | D9: =Sheet2!H10 -> 0.43761085 | E9: =Sheet2!I10 -> 13.58909 | F9: =Sheet2!L10 -> 6.31 | G9: =LN(Sheet2!M10) -> 5.0267797
A10: 40422 | B10: =LN(Sheet2!B11) -> 9.0964996 | C10: =Sheet2!E11 -> 3.2055348 | D10: =Sheet2!H11 -> 0.49080285 | E10: =Sheet2!I11 -> 13.622509 | F10: =Sheet2!L11 -> 6.31 | G10: =LN(Sheet2!M11) -> 5.0082597
A11: 40452 | B11: =LN(Sheet2!B12) -> 9.0969477 | C11: =Sheet2!E12 -> 3.5835699 | D11: =Sheet2!H12 -> 0.4947298 | E11: =Sheet2!I12 -> 13.659331 | F11: =Sheet2!L12 -> 6.31 | G11: =LN(Sheet2!M12) -> 4.876868
A12: 40483 | B12: =LN(Sheet2!B13) -> 9.1064233 | C12: =Sheet2!E13 -> 3.6371591 | D12: =Sheet2!H13 -> 0.40386221 | E12: =Sheet2!I13 -> 13.649567 | F12: =Sheet2!L13 -> 6.31 | G12: =LN(Sheet2!M13) -> 4.9240268
A13: 40513 | B13: =LN(Sheet2!B14) -> 9.1039794 | C13: =Sheet2!E14 -> 3.6214708 | D13: =Sheet2!H14 -> 0.43550412 | E13: =Sheet2!I14 -> 13.670625 | F13: =Sheet2!L14 -> 6.32 | G13: =LN(Sheet2!M14) -> 4.8766642
... A202: 46266 | B202: =LN(Sheet2!B203) -> 9.7912702 | C202: =Sheet2!E203 -> 0.6 | D202: =Sheet2!H203 -> 0.52637803 | E202: =Sheet2!I203 -> 14.44793 | F202: =Sheet2!L203 -> 1.87 | G202: =LN(Sheet2!M203) -> 4.5129452

Sheet Sheet2
B1: xr | C1: Core inflation | E1: Differential | F1: Export price | G1: Import price | H1: tot | I1: nfa | J1: bi_rate | K1: ffr_rate | L1: ir_diff | M1: cds5y | O1: xr_eop | P1: xr
A2: date | C2: Indonesia | D2: US
A3: 40179 | B3: =O3 -> 9365 | C3: 4.4288415 | D3: 1.51234 | E3: =C3-D3 -> 2.9165015 | F3: =Sheet3!D19/Sheet3!C19 -> 0.26518155 | G3: =Sheet3!E19/Sheet3!F19 -> 0.86869503 | H3: =F3/G3 -> 0.30526427 | I3: =LN(Sheet3!B19) -> 13.479959 | J3: 6.5 | K3: 0.11 | L3: =J3-K3 -> 6.39 | M3: 191.34248 | O3: 9365 | P3: 9285.6667
A4: 40210 | B4: =O4 -> 9335 | C4: 3.8805436 | D4: 1.34945 | E4: =C4-D4 -> 2.5310936 | F4: =Sheet3!D20/Sheet3!C20 -> 0.32493193 | G4: =Sheet3!E20/Sheet3!F20 -> 0.85152386 | H4: =F4/G4 -> 0.38158876 | I4: =LN(Sheet3!B20) -> 13.481849 | J4: 6.5 | K4: 0.13 | L4: =J4-K4 -> 6.37 | M4: 202.83085 | O4: 9335 | P4: 9344.9
A5: 40238 | B5: =O5 -> 9115 | C5: 3.5599858 | D5: 1.15921 | E5: =C5-D5 -> 2.4007758 | F5: =Sheet3!D21/Sheet3!C21 -> 0.29842889 | G5: =Sheet3!E21/Sheet3!F21 -> 0.81970256 | H5: =F5/G5 -> 0.36406973 | I5: =LN(Sheet3!B21) -> 13.49557 | J5: 6.5 | K5: 0.16 | L5: =J5-K5 -> 6.34 | M5: 163.08357 | O5: 9115 | P5: 9167
A6: 40269 | B6: =O6 -> 9012 | C6: 3.6951295 | D6: 0.96751 | E6: =C6-D6 -> 2.7276196 | F6: =Sheet3!D22/Sheet3!C22 -> 0.32312633 | G6: =Sheet3!E22/Sheet3!F22 -> 0.82971103 | H6: =F6/G6 -> 0.38944441 | I6: =LN(Sheet3!B22) -> 13.559525 | J6: 6.5 | K6: 0.2 | L6: =J6-K6 -> 6.3 | M6: 159.84155 | O6: 9012 | P6: 9030.4091
A7: 40299 | B7: =O7 -> 9180 | C7: 3.8146897 | D7: 0.94014 | E7: =C7-D7 -> 2.8745497 | F7: =Sheet3!D23/Sheet3!C23 -> 0.32028026 | G7: =Sheet3!E23/Sheet3!F23 -> 0.85790101 | H7: =F7/G7 -> 0.37333009 | I7: =LN(Sheet3!B23) -> 13.506323 | J7: 6.5 | K7: 0.2 | L7: =J7-K7 -> 6.3 | M7: 186.46043 | O7: 9180 | P7: 9172.9048
A8: 40330 | B8: =O8 -> 9083 | C8: 3.9669862 | D8: 0.9502 | E8: =C8-D8 -> 3.0167862 | F8: =Sheet3!D24/Sheet3!C24 -> 0.30916141 | G8: =Sheet3!E24/Sheet3!F24 -> 0.85135745 | H8: =F8/G8 -> 0.36313937 | I8: =LN(Sheet3!B24) -> 13.536574 | J8: 6.5 | K8: 0.18 | L8: =J8-K8 -> 6.32 | M8: 182.34555 | O8: 9083 | P8: 9146.2727
A9: 40360 | B9: =O9 -> 8952 | C9: 4.1493409 | D9: 0.95775 | E9: =C9-D9 -> 3.1915909 | F9: =Sheet3!D25/Sheet3!C25 -> 0.34517267 | G9: =Sheet3!E25/Sheet3!F25 -> 0.78229113 | H9: =F9/G9 -> 0.44123301 | I9: =LN(Sheet3!B25) -> 13.543568 | J9: 6.5 | K9: 0.18 | L9: =J9-K9 -> 6.32 | M9: 166.68695 | O9: 8952 | P9: 9041.3182
A10: 40391 | B10: =O10 -> 9041 | C10: 4.2371388 | D10: 0.9171 | E10: =C10-D10 -> 3.3200388 | F10: =Sheet3!D26/Sheet3!C26 -> 0.34672355 | G10: =Sheet3!E26/Sheet3!F26 -> 0.79231024 | H10: =F10/G10 -> 0.43761085 | I10: =LN(Sheet3!B26) -> 13.58909 | J10: 6.5 | K10: 0.19 | L10: =J10-K10 -> 6.31 | M10: 152.44132 | O10: 9041 | P10: 8972.4091
A11: 40422 | B11: =O11 -> 8924 | C11: 4.0199248 | D11: 0.81439 | E11: =C11-D11 -> 3.2055348 | F11: =Sheet3!D27/Sheet3!C27 -> 0.36698953 | G11: =Sheet3!E27/Sheet3!F27 -> 0.7477331 | H11: =F11/G11 -> 0.49080285 | I11: =LN(Sheet3!B27) -> 13.622509 | J11: 6.5 | K11: 0.19 | L11: =J11-K11 -> 6.31 | M11: 149.64409 | O11: 8924 | P11: 8974.1818
A12: 40452 | B12: =O12 -> 8928 | C12: 4.1862899 | D12: 0.60272 | E12: =C12-D12 -> 3.5835699 | F12: =Sheet3!D28/Sheet3!C28 -> 0.38314512 | G12: =Sheet3!E28/Sheet3!F28 -> 0.77445329 | H12: =F12/G12 -> 0.4947298 | I12: =LN(Sheet3!B28) -> 13.659331 | J12: 6.5 | K12: 0.19 | L12: =J12-K12 -> 6.31 | M12: 131.21905 | O12: 8928 | P12: 8930.0476
A13: 40483 | B13: =O13 -> 9013 | C13: 4.3092191 | D13: 0.67206 | E13: =C13-D13 -> 3.6371591 | F13: =Sheet3!D29/Sheet3!C29 -> 0.32739222 | G13: =Sheet3!E29/Sheet3!F29 -> 0.81065327 | H13: =F13/G13 -> 0.40386221 | I13: =LN(Sheet3!B29) -> 13.649567 | J13: 6.5 | K13: 0.19 | L13: =J13-K13 -> 6.31 | M13: 137.55541 | O13: 9013 | P13: 8943.3636
A14: 40513 | B14: =O14 -> 8991 | C14: 4.2833608 | D14: 0.66189 | E14: =C14-D14 -> 3.6214708 | F14: =Sheet3!D30/Sheet3!C30 -> 0.35801063 | G14: =Sheet3!E30/Sheet3!F30 -> 0.82206025 | H14: =F14/G14 -> 0.43550412 | I14: =LN(Sheet3!B30) -> 13.670625 | J14: 6.5 | K14: 0.18 | L14: =J14-K14 -> 6.32 | M14: 131.1923 | O14: 8991 | P14: 9025
... A191: 45901 | B191: =O191 -> 16680 | C191: 2.1859488 | D191: 3.01997 | E191: =C191-D191 -> -0.83402116 | F191: =Sheet3!D207/Sheet3!C207 -> 0.39711415 | G191: =Sheet3!E207/Sheet3!F207 -> 1.0435443 | H191: =F191/G191 -> 0.38054363 | I191: =LN(Sheet3!B207) -> 14.550442 | J191: 4.75 | K191: 4.22 | L191: =J191-K191 -> 0.53 | M191: 73.989818 | O191: 16680 | P191: 16514.136
A192: 45931 | B192: =O192 -> 16640 | C192: 2.3621297 | D192: =AVERAGE(D191,D193) -> 2.809505 | E192: =C192-D192 -> -0.44737527 | F192: =Sheet3!D208/Sheet3!C208 -> 0.37333818 | G192: =Sheet3!E208/Sheet3!F208 -> 1.0598189 | H192: =F192/G192 -> 0.35226601 | I192: =LN(Sheet3!B208) -> 14.545356 | J192: 4.75 | K192: 4.09 | L192: =J192-K192 -> 0.66 | M192: 79.221957 | O192: 16640 | P192: 16583.13
A193: 45962 | B193: =O193 -> 16644 | C193: 2.3580869 | D193: 2.59904 | E193: =C193-D193 -> -0.24095309 | F193: =Sheet3!D209/Sheet3!C209 -> 0.34735712 | G193: =Sheet3!E209/Sheet3!F209 -> 1.0032413 | H193: =F193/G193 -> 0.34623487 | I193: =LN(Sheet3!B209) -> 14.543405 | J193: 4.75 | K193: 3.88 | L193: =J193-K193 -> 0.87 | M193: 75.4482 | O193: 16644 | P193: 16692.45
A194: 45992 | B194: =O194 -> 16782 | C194: 2.3825344 | D194: 2.64648 | E194: =C194-D194 -> -0.26394559 | F194: =Sheet3!D210/Sheet3!C210 -> 0.37174855 | G194: =Sheet3!E210/Sheet3!F210 -> 1.0347571 | H194: =F194/G194 -> 0.35926166 | I194: =LN(Sheet3!B210) -> 14.585117 | J194: 4.75 | K194: 3.72 | L194: =J194-K194 -> 1.03 | M194: 71.11987 | O194: 16782 | P194: 16702.217
A195: 46023 | B195: =O195 -> 16786 | C195: 2.4510268 | D195: 2.51203 | E195: =C195-D195 -> -0.06100322 | F195: =Sheet3!D211/Sheet3!C211 -> 0.39399007 | G195: =Sheet3!E211/Sheet3!F211 -> 0.92702447 | H195: =F195/G195 -> 0.42500503 | I195: =LN(Sheet3!B211) -> 14.581624 | J195: 4.75 | K195: 3.64 | L195: =J195-K195 -> 1.11 | M195: 72.201045 | O195: 16786 | P195: 16814.864
A196: 46054 | B196: =O196 -> 16758 | C196: 2.6338148 | D196: 2.47246 | E196: =C196-D196 -> 0.16135478 | F196: =Sheet3!D212/Sheet3!C212 -> 0.42134055 | G196: =Sheet3!E212/Sheet3!F212 -> 0.94223827 | H196: =F196/G196 -> 0.44716986 | I196: =LN(Sheet3!B212) -> 14.554432 | J196: 4.75 | K196: 3.64 | L196: =J196-K196 -> 1.11 | M196: 80.08935 | O196: 16758 | P196: 16815.35
A197: 46082 | B197: =O197 -> 16993 | C197: 2.5240158 | D197: 2.60217 | E197: =C197-D197 -> -0.07815418 | F197: =Sheet3!D213/Sheet3!C213 -> 0.41799464 | G197: =Sheet3!E213/Sheet3!F213 -> 1.1021863 | H197: =F197/G197 -> 0.37924138 | I197: =LN(Sheet3!B213) -> 14.558505 | J197: 4.75 | K197: 3.64 | L197: =J197-K197 -> 1.11 | M197: 93.777091 | O197: 16993 | P197: 16935.045
A198: 46113 | B198: =O198 -> 17324 | C198: 2.4410853 | D198: 2.8 | E198: =C198-D198 -> -0.35891466 | F198: =Sheet3!D214/Sheet3!C214 -> 0.47080141 | G198: =Sheet3!E214/Sheet3!F214 -> 1.0469817 | H198: =F198/G198 -> 0.44967494 | I198: =LN(Sheet3!B214) -> 14.534566 | J198: 4.75 | K198: 3.64 | L198: =J198-K198 -> 1.11 | M198: 88.659409 | O198: 17324 | P198: 17138.591
A199: 46143 | B199: =O199 -> 17789 | C199: 2.59 | D199: 2.9 | E199: =C199-D199 -> -0.31 | F199: =Sheet3!D215/Sheet3!C215 -> 0.42408486 | G199: =Sheet3!E215/Sheet3!F215 -> 0.90346576 | H199: =F199/G199 -> 0.46939782 | I199: =LN(Sheet3!B215) -> 14.536409 | J199: 5.25 | K199: 3.63 | L199: =J199-K199 -> 1.62 | M199: 88.392947 | O199: 17789 | P199: 17542.316
A200: 46174 | B200: =O200 -> 17962 | C200: 2.76 | D200: 2.6 | E200: =C200-D200 -> 0.16 | F200: =Sheet3!D216/Sheet3!C216 -> 0.45040661 | G200: =Sheet3!E216/Sheet3!F216 -> 0.96480948 | H200: =F200/G200 -> 0.46683476 | I200: =LN(Sheet3!B216) -> 14.458141 | J200: 5.75 | K200: 3.63 | L200: =J200-K200 -> 2.12 | M200: 89.87 | O200: 17962 | P200: 17905.5
A201: 46204 | B201: =O201 -> 18058 | C201: 2.76 | D201: 2.5 | E201: =C201-D201 -> 0.26 | F201: =Sheet3!D217/Sheet3!C217 -> 0.47315046 | G201: =Sheet3!E217/Sheet3!F217 -> 0.99519964 | H201: =F201/G201 -> 0.47543271 | I201: =LN(Sheet3!B217) -> 14.448034 | J201: 5.75 | K201: 3.63 | L201: =J201-K201 -> 2.12 | M201: 93.36 | O201: 18058 | P201: 18014.478
A202: 46235 | B202: =O202 -> 17746 | C202: 2.92 | D202: 2.4 | E202: =C202-D202 -> 0.52 | F202: =Sheet3!D218/Sheet3!C218 -> 0.30374424 | G202: =Sheet3!E218/Sheet3!F218 -> 0.90384589 | H202: =F202/G202 -> 0.33605755 | I202: =LN(Sheet3!B218) -> 14.439325 | J202: 5.75 | K202: 3.63 | L202: =J202-K202 -> 2.12 | M202: 84.57 | O202: 17746 | P202: 17832.895
A203: 46266 | B203: =O203 -> 17877 | C203: 3.1 | D203: 2.5 | E203: =C203-D203 -> 0.6 | F203: =Sheet3!D219/Sheet3!C219 -> 0.51840951 | G203: =Sheet3!E219/Sheet3!F219 -> 0.98486161 | H203: =F203/G203 -> 0.52637803 | I203: =LN(Sheet3!B219) -> 14.44793 | J203: 5.75 | K203: =K202+0.25 -> 3.88 | L203: =J203-K203 -> 1.87 | M203: 91.19 | O203: 17877 | P203: 17749

Sheet Sheet3
A1: Select this link and click Refresh/Edit Download to update data and add or remove series | B1: BM (M2): Net Foreign Asset | C1: Exports: fob: Volume | D1: Export: fob | E1: Import: cif: Volume | F1: Import: cif | J1: =B1 -> BM (M2): Net Foreign Asset | K1: =C1 -> Exports: fob: Volume | L1: =D1 -> Export: fob | M1: =E1 -> Import: cif: Volume | N1: =F1 -> Import: cif | O1: Trade Balance
A2: Frequency | B2: Monthly | C2: Monthly | D2: Monthly | E2: Monthly | F2: Monthly
A3: Unit | B3: IDR bn | C3: kg mn | D3: USD mn | E3: kg mn | F3: USD mn | J3: % YoY | K3: % YoY | L3: % YoY | M3: % YoY | N3: % YoY | O3: USD mn
A4: Source | B4: Bank Indonesia | C4: Statistics Indonesia | D4: Statistics Indonesia | E4: Statistics Indonesia | F4: Statistics Indonesia
A5: Series ID | B5: 64074501 (DKCBGE) | C5: 13957201 (DJHA) | D5: 13920901 (DJAA) | E5: 195490802 (DJHC) | F5: 78865602 (DJAJAA)
A6: Last Obs. Date | B6: 46113 | C6: 46082 | D6: 46082 | E6: 46082 | F6: 46082
A7: 39814 | B7: 603620.23 | C7: 21833.053 | D7: 7280.1096 | E7: 6408.5336 | F7: 6600.5692
A8: 39845 | B8: 644002.67 | C8: 17010.589 | D8: 7134.3193 | E8: 5353.8121 | F8: 5939.0433
A9: 39873 | B9: 691464.7 | C9: 26431.789 | D9: 8614.7259 | E9: 5977.6943 | F9: 6554.1292
A10: 39904 | B10: 662715.31 | C10: 28870.407 | D10: 8453.9571 | E10: 6805.8893 | F10: 6706.762
A11: 39934 | B11: 666394.16 | C11: 28242.529 | D11: 9208.7741 | E11: 7567.752 | F11: 7641.2866
A12: 39965 | B12: 655439.78 | C12: 25855.872 | D12: 9381.4791 | E12: 8208.6258 | F12: 7935.4749
A13: 39995 | B13: 644557.88 | C13: 35327.714 | D13: 9684.1459 | E13: 7865.271 | F13: 8683.3419
A14: 40026 | B14: 650342.37 | C14: 37719.828 | D14: 10543.778 | E14: 8493.6002 | F14: 9707.3027
A15: 40057 | B15: 658645.31 | C15: 35100.516 | D15: 9842.5717 | E15: 8855.6127 | F15: 8516.6033
A16: 40087 | B16: 663980.84 | C16: 42329.715 | D16: 12242.673 | E16: 9229.601 | F16: 9430.1265
A17: 40118 | B17: 692831.7 | C17: 37472.63 | D17: 10775.362 | E17: 7715.4245 | F17: 8814.6574
A18: 40148 | B18: 679447.68 | C18: 42804.46 | D18: 13348.131 | E18: 8872.5893 | F18: 10299.948
... A202: 45748 | B202: 1980073.4 | C202: 53282.379 | D202: 20743.847 | E202: 18535.373 | F202: 20585.014
A203: 45778 | B203: 1955415.5 | C203: 59121.871 | D203: 24613.801 | E203: 20346.86 | F203: 20312.3 | J203: =B203/B191*100-100 -> 3.8653005 | K203: =C203/C191*100-100 -> -3.2225125 | L203: =D203/D191*100-100 -> 9.6775002 | M203: =E203/E191*100-100 -> 6.1209915 | N203: =F203/F191*100-100 -> 4.1376899 | O203: =D203-F203 -> 4301.5008
A204: 45809 | B204: 1964883.7 | C204: 52350.063 | D204: 23436.5 | E204: 20416.128 | F204: 19333 | J204: =B204/B192*100-100 -> 3.9070064 | K204: =C204/C192*100-100 -> -12.486028 | L204: =D204/D192*100-100 -> 11.293664 | M204: =E204/E192*100-100 -> 10.662452 | N204: =F204/F192*100-100 -> 4.2809177 | O204: =D204-F204 -> 4103.5
A205: 45839 | B205: 2004123.1 | C205: 58900.106 | D205: 24748.9 | E205: 19909.395 | F205: 20575.4 | J205: =B205/B193*100-100 -> 7.2821646 | K205: =C205/C193*100-100 -> -1.5626281 | L205: =D205/D193*100-100 -> 9.8640358 | M205: =E205/E193*100-100 -> -11.068239 | N205: =F205/F193*100-100 -> -5.8574371 | O205: =D205-F205 -> 4173.5
A206: 45870 | B206: 2024902.7 | C206: 66826.193 | D206: 24963.2 | E206: 19944.28 | F206: 19475.2 | J206: =B206/B194*100-100 -> 10.717476 | K206: =C206/C194*100-100 -> 8.042864 | L206: =D206/D194*100-100 -> 5.7827864 | M206: =E206/E194*100-100 -> -2.6285906 | N206: =F206/F194*100-100 -> -6.5643296 | O206: =D206-F206 -> 5488
A207: 45901 | B207: 2085339.8 | C207: 62146.112 | D207: 24679.1 | E207: 21220.787 | F207: 20335.3 | J207: =B207/B195*100-100 -> 12.586247 | K207: =C207/C195*100-100 -> -1.021981 | L207: =D207/D195*100-100 -> 11.414334 | M207: =E207/E195*100-100 -> 13.563162 | N207: =F207/F195*100-100 -> 7.1743149 | O207: =D207-F207 -> 4343.8
A208: 45931 | B208: 2074759.4 | C208: 64917.818 | D208: 24236.3 | E208: 23149.731 | F208: 21843.1 | J208: =B208/B196*100-100 -> 10.350927 | K208: =C208/C196*100-100 -> -4.9622261 | L208: =D208/D196*100-100 -> -2.3076489 | M208: =E208/E196*100-100 -> 2.3895697 | N208: =F208/F196*100-100 -> -1.1526034 | O208: =D208-F208 -> 2393.2
A209: 45962 | B209: 2070716.9 | C209: 64834.716 | D209: 22520.8 | E209: 19922.855 | F209: 19858.488 | J209: =B209/B197*100-100 -> 9.7170525 | K209: =C209/C197*100-100 -> -1.9787194 | L209: =D209/D197*100-100 -> -6.6019152 | M209: =E209/E197*100-100 -> 1.8719744 | N209: =F209/F197*100-100 -> 0.45618375 | O209: =D209-F209 -> 2662.312
A210: 45992 | B210: 2158916.4 | C210: 70872.636 | D210: 26346.8 | E210: 24662.458 | F210: 23834.055 | J210: =B210/B198*100-100 -> 8.887652 | K210: =C210/C198*100-100 -> 5.8110614 | L210: =D210/D198*100-100 -> 11.640915 | M210: =E210/E198*100-100 -> 18.112281 | N210: =F210/F198*100-100 -> 10.807698 | O210: =D210-F210 -> 2512.745
A211: 46023 | B211: 2151389 | C211: 56234.159 | D211: 22155.7 | E211: 19654.17 | F211: 21201.35 | J211: =B211/B199*100-100 -> 5.53727 | K211: =C211/C199*100-100 -> 1.7776719 | L211: =D211/D199*100-100 -> 3.3946591 | M211: =E211/E199*100-100 -> 25.510528 | N211: =F211/F199*100-100 -> 18.206122 | O211: =D211-F211 -> 954.34987
A212: 46054 | B212: 2093675.1 | C212: 52610.175 | D212: 22166.8 | E212: 19686.702 | F212: 20893.549 | J212: =B212/B200*100-100 -> 1.9551465 | K212: =C212/C200*100-100 -> -7.0800896 | L212: =D212/D200*100-100 -> 1.0144823 | M212: =E212/E200*100-100 -> -2.2770382 | N212: =F212/F200*100-100 -> 10.846992 | O212: =D212-F212 -> 1273.2509
A213: 46082 | B213: 2102220.3 | C213: 53892.528 | D213: 22526.788 | E213: 21168.35 | F213: 19205.783 | J213: =B213/B201*100-100 -> 2.7195543 | K213: =C213/C201*100-100 -> -6.5146906 | L213: =D213/D201*100-100 -> -3.0991803 | M213: =E213/E201*100-100 -> 11.398231 | N213: =F213/F201*100-100 -> 1.5105985 | O213: =D213-F213 -> 3321.0051
A214: 46113 | B214: 2052493.1 | C214: 53744.114 | D214: 25302.805 | E214: 26398.289 | F214: 25213.708 | J214: =B214/B202*100-100 -> 3.6574216 | K214: =C214/C202*100-100 -> 0.86658107 | L214: =D214/D202*100-100 -> 21.977399 | M214: =E214/E202*100-100 -> 42.421136 | N214: =F214/F202*100-100 -> 22.485743 | O214: =D214-F214 -> 89.09722
... A217: 46204 | B217: 1882355.3 | C217: 55408.831 | D217: 26216.714 | E217: 25969.546 | F217: 26094.81 | J217: =B217/B205*100-100 -> -6.0758644 | K217: =C217/C205*100-100 -> -5.9274517 | L217: =D217/D205*100-100 -> 5.9308238 | M217: =E217/E205*100-100 -> 30.438647 | N217: =F217/F205*100-100 -> 26.825288 | O217: =D217-F217 -> 121.90336
A218: 46235 | B218: =B206*(1+J218%) -> 1866032.3 | C218: =C206*(1+K218%) -> 87609.139 | D218: =D206*(1+L218%) -> 26610.771 | E218: =E206*(1+M218%) -> 22038.429 | F218: =F206*(1+N218%) -> 24382.95 | G218: *Data DJBC | H218: *Updated Data BPS | J218: =_xlfn.FORECAST.LINEAR(J217,J206:J217,J205:J216) -> -7.8458244 | K218: 31.1 | L218: 6.6 | M218: 10.5 | N218: 25.2 | O218: =D218-F218 -> 2227.8208 | P218: *Data DJBC | Q218: *Updated Data BPS
A219: 46266 | B219: =B207*(1+J219%) -> 1882159.4 | C219: =C207*(1+K219%) -> 49192.53 | D219: =D207*(1+L219%) -> 25501.875 | E219: =E207*(1+M219%) -> 24573.1 | F219: =F207*(1+N219%) -> 24950.815 | J219: =_xlfn.FORECAST.LINEAR(J218,J207:J218,J206:J217) -> -9.7432749 | K219: =_xlfn.FORECAST.LINEAR(K218,K207:K218,K206:K217) -> -20.843753 | L219: =_xlfn.FORECAST.LINEAR(L218,L207:L218,L206:L217) -> 3.3338958 | M219: =_xlfn.FORECAST.LINEAR(M218,M207:M218,M206:M217) -> 15.79731 | N219: =_xlfn.FORECAST.LINEAR(N218,N207:N218,N206:N217) -> 22.69706 | O219: =D219-F219 -> 551.06019 | P219: *Hasil linear forecast dari growth nya

Sheet Sheet1
A1: date | B1: xr | C1: infl_diff | D1: tot | E1: nfa | F1: ir_diff | G1: cds
A2: 46113 | B2: =LN(Sheet2!B198) -> 9.7598481 | C2: =Sheet2!E198 -> -0.35891466 | D2: =Sheet2!H198 -> 0.44967494 | E2: =Sheet2!I198 -> 14.534566 | F2: =Sheet2!L198 -> 1.11 | G2: =LN(Sheet2!M198) -> 4.4848022
A3: 46143 | B3: =LN(Sheet2!B199) -> 9.7863356 | C3: =Sheet2!E199 -> -0.31 | D3: =Sheet2!H199 -> 0.46939782 | E3: =Sheet2!I199 -> 14.536409 | F3: =Sheet2!L199 -> 1.62 | G3: =LN(Sheet2!M199) -> 4.4817922
